[{"beatmapset_id":"1235121","beatmap_id":"2567564","approved":"1","total_length":"222","hit_length":"220","version":"Nostalgia","file_md5":"2758a5add775ea1ed3979dba0111773a","diff_size":"4","diff_overall":"9","diff_approach":"9.6","diff_drain":"6","mode":"0","count_normal":"767","count_slider":"402","count_spinner":"0","submit_date":"2020-08-13 10:21:03","approved_date":"2021-03-06 16:42:46","last_update":"2021-02-23 13:13:03","artist":"Fujikawa Chiai","artist_unicode":"藤川千愛","title":"Gomi no Hi","title_unicode":"ゴミの日","creator":"a_Blue","creator_id":"5645667","bpm":"248","source":"","tags":"laika ライカ japanese rock furuya kan 古谷完 fujinaga ryutaro 藤永龍太郎 ablue","genre_id":"4","language_id":"3","favourite_count":"503","rating":"9.34251","storyboard":"0","video":"0","download_unavailable":"0","audio_unavailable":"0","playcount":"114481","passcount":"5817","packs":"S993","max_combo":"1625","diff_aim":"3.77607","diff_speed":"3.14942","difficultyrating":"7.30313"},{"beatmapset_id":"1780039","beatmap_id":"3645402","approved":"-2","total_length":"119","hit_length":"118","version":"Are you a Street fan? ok name me every street","file_md5":"843d39d4a05b8e68cccfdaf91e80bd63","diff_size":"4.3","diff_overall":"9","diff_approach":"9.6","diff_drain":"5","mode":"0","count_normal":"589","count_slider":"229","count_spinner":"0","submit_date":"2022-06-06 14:38:21","approved_date":null,"last_update":"2022-06-06 18:13:09","artist":"Street","artist_unicode":"Street","title":"Phi","title_unicode":"Φ","creator":"GYGY","creator_id":"7201269","bpm":"190","source":"","tags":"","genre_id":"10","language_id":"5","favourite_count":"3","rating":"0","storyboard":"0","video":"0","download_unavailable":"0","audio_unavailable":"0","playcount":"228","passcount":"21","packs":null,"max_combo":"1146","diff_aim":"3.46127","diff_speed":"3.30873","difficultyrating":"7.07643"},{"beatmapset_id":"1802422","beatmap_id":"3772455","approved":"-2","total_length":"208","hit_length":"204","version":"mix deez nuts","file_md5":"296607af35b8a565d24cb2d7a2fc8bb7","diff_size":"4","diff_overall":"9.4","diff_approach":"9.7","diff_drain":"6","mode":"0","count_normal":"607","count_slider":"557","count_spinner":"0","submit_date":"2022-07-08 14:56:11","approved_date":null,"last_update":"2022-11-25 14:55:31","artist":"Official HIGE DANdism","artist_unicode":"Official髭男dism","title":"Mixed Nuts","title_unicode":"ミックスナッツ","creator":"Amateurre","creator_id":"7326908","bpm":"150","source":"SPY×FAMILY","tags":"keqing iljaaz flake kyuuchie liyuu rielle anxient spy family スパイファミリー higedan anime japanese pop j-pop jpop jazz spyxfamily","genre_id":"5","language_id":"3","favourite_count":"37","rating":"0","storyboard":"0","video":"0","download_unavailable":"0","audio_unavailable":"0","playcount":"1612","passcount":"221","packs":null,"max_combo":"1759","diff_aim":"3.47289","diff_speed":"2.91674","difficultyrating":"6.73345"},{"beatmapset_id":"1322727","beatmap_id":"2739798","approved":"1","total_length":"190","hit_length":"189","version":"?","file_md5":"b57a8080951e3e4f978f21f3abd32e5b","diff_size":"4","diff_overall":"8.5","diff_approach":"9.5","diff_drain":"7","mode":"0","count_normal":"473","count_slider":"461","count_spinner":"0","submit_date":"2020-12-13 17:44:45","approved_date":"2021-04-04 20:42:23","last_update":"2021-03-28 11:32:17","artist":"Ado","artist_unicode":"Ado","title":"USSEEWA","title_unicode":"うっせぇわ","creator":"Ryuusei Aika","creator_id":"7777875","bpm":"178","source":"","tags":"アド syudou japanese rock jrock j-rock pop jpop j-pop female vocal nuvolina coloured glazee coloured_glazee amateurre head dada hinamommy kimikamymommy a_blue ts8zs","genre_id":"4","language_id":"3","favourite_count":"10408","rating":"9.22104","storyboard":"0","video":"1","download_unavailable":"0","audio_unavailable":"0","playcount":"262486","passcount":"17120","packs":"S1006","max_combo":"1471","diff_aim":"3.97784","diff_speed":"2.75138","difficultyrating":"7.29129"},{"beatmapset_id":"1310159","beatmap_id":"2715945","approved":"-2","total_length":"172","hit_length":"150","version":"The Darkness That Surrounds My Soul Only Makes Me Stronger","file_md5":"2a8343e93a9555b6373fd3dc1c7fb494","diff_size":"4","diff_overall":"9.3","diff_approach":"9.7","diff_drain":"4","mode":"0","count_normal":"634","count_slider":"368","count_spinner":"2","submit_date":"2020-11-27 12:39:23","approved_date":null,"last_update":"2020-11-29 06:03:18","artist":"Camellia","artist_unicode":"かめりあ","title":"Blackmagik Blazing (Cut Ver.)","title_unicode":"Blackmagik Blazing (Cut Ver.)","creator":"Lunicia","creator_id":"4369309","bpm":"256","source":"","tags":"cametek speed","genre_id":"10","language_id":"13","favourite_count":"17","rating":"0","storyboard":"0","video":"0","download_unavailable":"0","audio_unavailable":"0","playcount":"5131","passcount":"1204","packs":null,"max_combo":"1469","diff_aim":"3.44601","diff_speed":"3.72809","difficultyrating":"7.50788"},{"beatmapset_id":"1567583","beatmap_id":"3200715","approved":"-2","total_length":"162","hit_length":"151","version":"Chrysoberyl","file_md5":"10eb239a5b8718b1bd070289636075c2","diff_size":"4.2","diff_overall":"8.5","diff_approach":"9.3","diff_drain":"5","mode":"0","count_normal":"622","count_slider":"211","count_spinner":"0","submit_date":"2021-09-03 13:29:55","approved_date":null,"last_update":"2021-09-08 04:55:28","artist":"onoken","artist_unicode":"onoken","title":"Alexandrite","title_unicode":"Alexandrite","creator":"iLyne","creator_id":"13924533","bpm":"175","source":"","tags":"omc 8 osu fan cafe mapping contest","genre_id":"10","language_id":"5","favourite_count":"0","rating":"0","storyboard":"0","video":"0","download_unavailable":"0","audio_unavailable":"0","playcount":"56","passcount":"8","packs":null,"max_combo":"1173","diff_aim":"3.31271","diff_speed":"3.15099","difficultyrating":"6.7572"},{"beatmapset_id":"1485831","beatmap_id":"3046747","approved":"-2","total_length":"122","hit_length":"122","version":"aww shidd","file_md5":"9c237c9d2ff2100e47595c68d652c81d","diff_size":"3.5","diff_overall":"8","diff_approach":"8","diff_drain":"5","mode":"0","count_normal":"415","count_slider":"247","count_spinner":"1","submit_date":"2021-06-07 16:46:45","approved_date":null,"last_update":"2021-06-07 16:47:03","artist":"Yasui Yousuke","artist_unicode":"安井 洋介","title":"YO-KAI Disco [MEIKAI ARRANGE VERSION]","title_unicode":"YO-KAI Disco [MEIKAI ARRANGE VERSION]","creator":"[Keqing]","creator_id":"8972308","bpm":"155","source":"まもるクンは呪われてしまった！","tags":"mamorukun curse! 冥界活劇アレンジトラックス hell's entrance world mamoru-kun wa norowarete shimatta! soundtrack https://sweeprecord.com/srin-1087/ g.rev cyberfront supersweep scubdomino anime girl natsume shiki jungkyuyoung","genre_id":"2","language_id":"5","favourite_count":"9","rating":"0","storyboard":"0","video":"0","download_unavailable":"0","audio_unavailable":"0","playcount":"2449","passcount":"429","packs":null,"max_combo":"914","diff_aim":"2.78594","diff_speed":"2.90576","difficultyrating":"5.94889"},{"beatmapset_id":"1496500","beatmap_id":"3385003","approved":"1","total_length":"241","hit_length":"241","version":"Extreme","file_md5":"a77d25090e9a5892ff34b9ba43055813","diff_size":"4.5","diff_overall":"9","diff_approach":"9.4","diff_drain":"5.5","mode":"0","count_normal":"899","count_slider":"454","count_spinner":"2","submit_date":"2021-06-19 16:06:21","approved_date":"2022-03-24 19:03:46","last_update":"2022-03-17 18:15:31","artist":"paraoka feat. haru*nya","artist_unicode":"paraoka feat. haru*nya","title":"Free Waltz","title_unicode":"フリーワルツ","creator":"Xilver15","creator_id":"3099689","bpm":"138","source":"","tags":"progressive jazz fusion rock bossa nova japanese koujimachi yousankan ongen doujin c78 comiket ぱらおか バベリズム 麹町養蚕館 paranoid masaoka パラノイド正岡","genre_id":"14","language_id":"3","favourite_count":"134","rating":"9.23438","storyboard":"0","video":"0","download_unavailable":"0","audio_unavailable":"0","playcount":"7111","passcount":"815","packs":"S1157","max_combo":"1915","diff_aim":"3.07039","diff_speed":"2.99268","difficultyrating":"6.33496"},{"beatmapset_id":"1318448","beatmap_id":"2731363","approved":"-2","total_length":"222","hit_length":"221","version":"Extra","file_md5":"74833d04be621b0d50595ade0695f4e9","diff_size":"4.2","diff_overall":"8.3","diff_approach":"9.6","diff_drain":"4.8","mode":"0","count_normal":"338","count_slider":"690","count_spinner":"3","submit_date":"2020-12-08 01:42:11","approved_date":null,"last_update":"2020-12-13 04:54:50","artist":"Silentroom","artist_unicode":"Silentroom","title":"Shuu no Hazama","title_unicode":"驟雨の狭間","creator":"Firika","creator_id":"9590557","bpm":"174","source":"","tags":"pdc pending cup 2020 pdc2020 mapping contest instrumental electronic neurofunk dnb drum n' bass drum and bass featured artist fa silentroom single rainshower rrtyui necho suzuki_1112 otosaka-yu rage quit frenz2019 polycube shun yamaguchi 駿 rumu","genre_id":"10","language_id":"5","favourite_count":"37","rating":"0","storyboard":"0","video":"0","download_unavailable":"0","audio_unavailable":"0","playcount":"757","passcount":"245","packs":null,"max_combo":"1855","diff_aim":"3.36535","diff_speed":"2.83604","difficultyrating":"6.53295"},{"beatmapset_id":"1910672","beatmap_id":"3941108","approved":"-2","total_length":"124","hit_length":"123","version":"Extreme","file_md5":"ecdbc68bc2d30eef9c209f0d87ede5dd","diff_size":"4.2","diff_overall":"9","diff_approach":"9.5","diff_drain":"6","mode":"0","count_normal":"317","count_slider":"313","count_spinner":"0","submit_date":"2022-12-26 13:52:14","approved_date":null,"last_update":"2022-12-26 13:52:20","artist":"25-ji, Nightcord de. x Kagamine Len","artist_unicode":"25時、ナイトコードで。 × 鏡音レン","title":"Bug","title_unicode":"バグ","creator":"Mocaotic","creator_id":"9487458","bpm":"186","source":"プロジェクトセカイ カラフルステージ！ feat. 初音ミク","tags":"hatsune miku: colorful stage! at 25:00 nightcode project sekai プロセカ proseka puroseka かいりきベア kairiki bear vocaloid cover hatsune miku 宵崎奏 yoisaki kanade 朝比奈まふゆ asahina mafuyu 東雲絵名 shinonome ena 暁山瑞希 akiyama mizuki 楠木ともり tomori kusunoki 田辺留依 tanabe rui 鈴木みのり suzuki minori 佐藤日向 sato hinata japanese pop jpop j-pop electronic video rhythm mobile game gst:live2022 great singapore tournament live 2022 gstlive custom map tourney aef asia esports festival online kallang wave mall exp esports experience center gstlive2022c8","genre_id":"4","language_id":"3","favourite_count":"2","rating":"0","storyboard":"0","video":"0","download_unavailable":"0","audio_unavailable":"0","playcount":"70","passcount":"15","packs":null,"max_combo":"951","diff_aim":"3.5672","diff_speed":"3.0569","difficultyrating":"6.96746"},{"beatmapset_id":"830266","beatmap_id":"1739583","approved":"1","total_length":"221","hit_length":"215","version":"Zero Vector","file_md5":"00010f0eb02ee131aacac54bf72d5444","diff_size":"5","diff_overall":"8","diff_approach":"8","diff_drain":"5","mode":"0","count_normal":"939","count_slider":"0","count_spinner":"0","submit_date":"2018-08-11 11:49:32","approved_date":"2019-04-02 17:20:03","last_update":"2019-03-26 15:42:07","artist":"Wang Yi Tao","artist_unicode":"王艺陶","title":"Zi You Sheng Guang","title_unicode":"自由圣光","creator":"Ryuusei Aika","creator_id":"7777875","bpm":"140","source":"凹凸世界","tags":"chinese anime aotu world 七创社 7doc 杨秉音 樱谙 asuka_- angelsnow present ayyri eiri-","genre_id":"3","language_id":"4","favourite_count":"99","rating":"8.35955","storyboard":"0","video":"0","download_unavailable":"0","audio_unavailable":"0","playcount":"44424","passcount":"5778","packs":"S757","max_combo":"939","diff_aim":"2.9655","diff_speed":"2.62647","difficultyrating":"5.86668"},{"beatmapset_id":"1884175","beatmap_id":"4027941","approved":"1","total_length":"199","hit_length":"190","version":"extra","file_md5":"ae2d591ba1a357945c64567bbc727a7e","diff_size":"4.3","diff_overall":"8.6","diff_approach":"9.3","diff_drain":"5.7","mode":"0","count_normal":"395","count_slider":"566","count_spinner":"0","submit_date":"2022-11-12 18:56:35","approved_date":"2023-03-10 23:25:49","last_update":"2023-03-03 14:32:26","artist":"Annabel","artist_unicode":"Annabel","title":"wormhole","title_unicode":"wormhole","creator":"Lince Cosmico","creator_id":"6070370","bpm":"180","source":"","tags":"pdc pdc2022 pending cup featured artist mapping contest pdc22 骗顶杯 fall into a lilac slumber irreversible acnozei maot trynna shouichi taguchi 田口 囁一 m3-41 yue y_u_e jazz fa japanese","genre_id":"14","language_id":"3","favourite_count":"105","rating":"8.21622","storyboard":"0","video":"0","download_unavailable":"0","audio_unavailable":"0","playcount":"2431","passcount":"373","packs":"S1283","max_combo":"1550","diff_aim":"3.30584","diff_speed":"2.73041","difficultyrating":"6.37203"},{"beatmapset_id":"902587","beatmap_id":"2060873","approved":"1","total_length":"193","hit_length":"186","version":"Celektus' Virtuoso","file_md5":"2c0bdf3cad1dd25747e46d4ed301aaa7","diff_size":"4","diff_overall":"9","diff_approach":"9.6","diff_drain":"8","mode":"0","count_normal":"859","count_slider":"245","count_spinner":"0","submit_date":"2018-12-30 15:23:25","approved_date":"2019-12-25 22:26:07","last_update":"2019-12-18 15:06:48","artist":"sokoninaru","artist_unicode":"そこに鳴る","title":"Tenohira de odoru","title_unicode":"掌で踊る","creator":"Smokeman","creator_id":"2140676","bpm":"215","source":"","tags":"ゼロ zero koga records j-pop j-rock japanese metal alternative indie rock math-rock celektus knightc0re knightcore","genre_id":"11","language_id":"3","favourite_count":"235","rating":"8.92896","storyboard":"0","video":"0","download_unavailable":"0","audio_unavailable":"0","playcount":"56268","passcount":"2781","packs":"S850","max_combo":"1388","diff_aim":"3.60585","diff_speed":"3.30781","difficultyrating":"7.23796"},{"beatmapset_id":"1273531","beatmap_id":"2646349","approved":"1","total_length":"285","hit_length":"276","version":"twilight","file_md5":"c07a3281a2020c29daf0708fac82eb78","diff_size":"4.4","diff_overall":"8","diff_approach":"9","diff_drain":"5","mode":"0","count_normal":"576","count_slider":"318","count_spinner":"0","submit_date":"2020-10-07 16:43:10","approved_date":"2020-10-20 15:25:09","last_update":"2020-10-13 15:02:25","artist":"anNina","artist_unicode":"anNina","title":"ombre","title_unicode":"ombre","creator":"Lasse","creator_id":"896613","bpm":"175","source":"","tags":"annabel bermei.inazawa japanese pop","genre_id":"5","language_id":"3","favourite_count":"81","rating":"9.34483","storyboard":"0","video":"0","download_unavailable":"0","audio_unavailable":"0","playcount":"26830","passcount":"5414","packs":"S944","max_combo":"1265","diff_aim":"3.786","diff_speed":"2.98497","difficultyrating":"7.18685"},{"beatmapset_id":"1936138","beatmap_id":"4001703","approved":"-1","total_length":"165","hit_length":"165","version":"Hell","file_md5":"90b0ccfb641effba0ad21ab23361b00d","diff_size":"4","diff_overall":"8","diff_approach":"8","diff_drain":"5","mode":"0","count_normal":"773","count_slider":"171","count_spinner":"1","submit_date":"2023-02-06 16:10:38","approved_date":null,"last_update":"2023-03-18 08:04:05","artist":"Danny Baranowsky","artist_unicode":"Danny Baranowsky","title":"Hot Damned (Ch 4 Light World)","title_unicode":"Hot Damned (Ch 4 Light World)","creator":"PandaHero","creator_id":"1233255","bpm":"160","source":"Super Meat Boy","tags":"vitas2222 video game instrumental rock","genre_id":"2","language_id":"5","favourite_count":"1","rating":"0","storyboard":"0","video":"0","download_unavailable":"0","audio_unavailable":"0","playcount":"3","passcount":"3","packs":null,"max_combo":"1186","diff_aim":"3.16666","diff_speed":"3.88614","difficultyrating":"7.456"},{"beatmapset_id":"623049","beatmap_id":"1313279","approved":"-2","total_length":"205","hit_length":"193","version":"rizumu","file_md5":"a6ec5c99d47dbc7a721b57dc631e4f99","diff_size":"4","diff_overall":"8","diff_approach":"8","diff_drain":"7","mode":"0","count_normal":"595","count_slider":"278","count_spinner":"0","submit_date":"2017-06-06 04:06:11","approved_date":null,"last_update":"2021-05-30 14:01:36","artist":"Gesu no Kiwami Otome.","artist_unicode":"ゲスの極み乙女。","title":"Romance ga Ariamaru","title_unicode":"ロマンスがありあまる","creator":"emilia","creator_id":"2003326","bpm":"170","source":"","tags":"enon kawatani kenta 「ストレイヤーズ・クロニクル」主題歌 indigo la end enon kawatani hip hop progressive","genre_id":"1","language_id":"1","favourite_count":"41","rating":"0","storyboard":"0","video":"0","download_unavailable":"0","audio_unavailable":"0","playcount":"2575","passcount":"365","packs":null,"max_combo":"1173","diff_aim":"3.40148","diff_speed":"3.58905","difficultyrating":"7.30875"},{"beatmapset_id":"1767671","beatmap_id":"3618327","approved":"1","total_length":"226","hit_length":"224","version":"AuroraE's Insane","file_md5":"6e274879e818478febbb9cc54b2e9022","diff_size":"4.5","diff_overall":"8","diff_approach":"9","diff_drain":"5","mode":"0","count_normal":"499","count_slider":"373","count_spinner":"3","submit_date":"2022-05-20 17:25:05","approved_date":"2022-06-06 16:21:16","last_update":"2022-05-29 03:09:51","artist":"NILFRUITS","artist_unicode":"煮ル果実","title":"Ironina","title_unicode":"アイロニーナ","creator":"Yugu","creator_id":"3161834","bpm":"140","source":"","tags":"japanese j-pop j pop jazz ボカロ ボーカロイド vocaloid popgato niru kajitsu aurorae pigeons vflower flower v-flower","genre_id":"5","language_id":"3","favourite_count":"128","rating":"9.15686","storyboard":"0","video":"0","download_unavailable":"0","audio_unavailable":"0","playcount":"8803","passcount":"1420","packs":"S1185","max_combo":"1292","diff_aim":"3.4078","diff_speed":"3.26061","difficultyrating":"6.97008"},{"beatmapset_id":"1282842","beatmap_id":"2664322","approved":"1","total_length":"313","hit_length":"311","version":"MAKE! SOME! NOISE!","file_md5":"fccc0d751993723ccb24e517d55063a3","diff_size":"4","diff_overall":"9.5","diff_approach":"9.8","diff_drain":"6.4","mode":"0","count_normal":"808","count_slider":"824","count_spinner":"0","submit_date":"2020-10-21 07:31:24","approved_date":"2021-01-28 14:27:00","last_update":"2021-01-20 01:49:05","artist":"Camellia","artist_unicode":"かめりあ","title":"We Could Get More Machinegun Psystyle! (And More Genre Switches)","title_unicode":"We Could Get More Machinegun Psystyle! (And More Genre Switches)","creator":"- Heatwave -","creator_id":"4166621","bpm":"160","source":"","tags":"blackmagik blackmagic blazing comiket 96 c96 cametek かめるかめりあ kamelcamellia comic market electronic fa featured artist instrumental 大箭将也 masaya oya cametek fullon psytrance hardcore techno bass music jungle terror psychedelic psytrance","genre_id":"10","language_id":"5","favourite_count":"667","rating":"9.62385","storyboard":"0","video":"0","download_unavailable":"0","audio_unavailable":"0","playcount":"404677","passcount":"36451","packs":"S979","max_combo":"2821","diff_aim":"3.31416","diff_speed":"3.32447","difficultyrating":"6.93503"}]